cursofiap_anv/__init__.py
cursofiap_anv/core.py
cursofiap_anv_package-1.0.0.dist-info/METADATA
cursofiap_anv_package-1.0.0.dist-info/WHEEL
cursofiap_anv_package-1.0.0.dist-info/top_level.txt
cursofiap_anv_package-1.0.0.dist-info/RECORD
