Metadata-Version: 2.4
Name: cursofiap_anv-package
Version: 1.0.0
Summary: Descricao da sua lib cursofiap_anv
Home-page: https://github.com/tadrianonet/cursofiap_anv
Author: Alexandre N Vicente
Author-email: seu.email@example.com
License: MIT
Dynamic: author
Dynamic: author-email
Dynamic: description
Dynamic: description-content-type
Dynamic: home-page
Dynamic: license
Dynamic: summary
